mzml2isa_qt/__init__.py
mzml2isa_qt/__main__.py
mzml2isa_qt/contact.py
mzml2isa_qt/main.py
mzml2isa_qt/ols.py
mzml2isa_qt/parserprogress.py
mzml2isa_qt/scrapers.py
mzml2isa_qt/usermeta.py
mzml2isa_qt/ontologies/pro.json
mzml2isa_qt/ontologies/pso.json
mzml2isa_qt/qt/__init__.py
mzml2isa_qt/qt/contact.py
mzml2isa_qt/qt/help.py
mzml2isa_qt/qt/main.py
mzml2isa_qt/qt/ols.py
mzml2isa_qt/qt/progress.py
mzml2isa_qt/qt/resources_rc.py
mzml2isa_qt/qt/usermeta.py
mzml2isa_qt-0.3.4.dist-info/DESCRIPTION.rst
mzml2isa_qt-0.3.4.dist-info/METADATA
mzml2isa_qt-0.3.4.dist-info/RECORD
mzml2isa_qt-0.3.4.dist-info/WHEEL
mzml2isa_qt-0.3.4.dist-info/entry_points.txt
mzml2isa_qt-0.3.4.dist-info/metadata.json
mzml2isa_qt-0.3.4.dist-info/top_level.txt
