Metadata-Version: 2.0
Name: mzml2isa-qt
Version: 0.3.4
Summary: A PyQt interface for mzml2isa parser.
Home-page: https://github.com/althonos/mzml2isa-qt
Author: Martin Larralde
Author-email: martin.larralde@ens-cachan.fr
License: GPLv3
Keywords: Metabolomics,Mass spectrometry,metabolites,ISA Tab,mzML,parsing
Platform: UNKNOWN
Classifier: Programming Language :: Python
Classifier: Programming Language :: Python :: 3
Classifier: Topic :: Text Processing :: Markup :: XML
Classifier: Topic :: Scientific/Engineering :: Bio-Informatics
Classifier: Topic :: Scientific/Engineering :: Interface Engine/Protocol Translator
Classifier: Topic :: Utilities
Classifier: Operating System :: OS Independent
Requires-Dist: PyQt5
Requires-Dist: mzml2isa
